pypsmb/__init__.py
pypsmb/__main__.py
pypsmb/entry.py
pypsmb/client/__init__.py
pypsmb/client/error.py
pypsmb/mb/__init__.py
pypsmb/mb/client_handler.py
pypsmb/mb/message_dispatcher.py
pypsmb/util/__init__.py
pypsmb/util/sockutil.py
pypsmb-0.1.2.dist-info/LICENSE
pypsmb-0.1.2.dist-info/METADATA
pypsmb-0.1.2.dist-info/WHEEL
pypsmb-0.1.2.dist-info/entry_points.txt
pypsmb-0.1.2.dist-info/top_level.txt
pypsmb-0.1.2.dist-info/RECORD
